setup.py
pyengine/__init__.py
pyengine/app.py
pyengine/my_class.py
pyengine/work.py
pyengine.egg-info/PKG-INFO
pyengine.egg-info/SOURCES.txt
pyengine.egg-info/dependency_links.txt
pyengine.egg-info/entry_points.txt
pyengine.egg-info/requires.txt
pyengine.egg-info/top_level.txt