Metadata-Version: 1.0
Name: pyengine
Version: 0.0.3
Summary: 
Home-page: http://www.gitee.com
Author: liuyancong
Author-email: 1437255447@qq.com
License: Apache License V2.0
Keywords: py,engine,run
Platform: any
